{
  "adsorbate": "Xe",
  "server": "Xe_2",
  "last_update": "2026-04-21T12:59:39.902220+00:00",
  "start_time": "2026-04-21T12:13:41.733592+00:00",
  "total_mofs": 208,
  "pressures": [
    0.1,
    0.5,
    1.0,
    2.0,
    3.0,
    4.0,
    5.0,
    6.0,
    7.0,
    8.0,
    9.0,
    10.0
  ],
  "per_pressure": {
    "0.1": {
      "completed": 7,
      "converged": 7,
      "failed": 0
    },
    "0.5": {
      "completed": 7,
      "converged": 7,
      "failed": 0
    },
    "1": {
      "completed": 7,
      "converged": 5,
      "failed": 2
    },
    "2": {
      "completed": 7,
      "converged": 5,
      "failed": 2
    },
    "3": {
      "completed": 7,
      "converged": 4,
      "failed": 3
    },
    "4": {
      "completed": 7,
      "converged": 3,
      "failed": 4
    },
    "5": {
      "completed": 7,
      "converged": 2,
      "failed": 5
    },
    "6": {
      "completed": 7,
      "converged": 1,
      "failed": 6
    },
    "7": {
      "completed": 7,
      "converged": 0,
      "failed": 7
    },
    "8": {
      "completed": 7,
      "converged": 1,
      "failed": 6
    },
    "9": {
      "completed": 7,
      "converged": 1,
      "failed": 6
    },
    "10": {
      "completed": 6,
      "converged": 1,
      "failed": 5
    }
  },
  "current_mof": "qmof-d3dcec0",
  "current_pressure": 9.0,
  "mof_set_info": {
    "shard_file": "/workspace/shards/Xe_rear/shard_Xe_6.txt",
    "shard_index": "6",
    "n_mofs": 208
  }
}