{
  "adsorbate": "Xe",
  "server": "Xe_2",
  "last_update": "2026-04-22T10:28:02.183808+00:00",
  "start_time": "2026-04-22T04:31:50.384368+00:00",
  "total_mofs": 208,
  "pressures": [
    0.1,
    0.5,
    1.0,
    2.0,
    3.0,
    4.0,
    5.0,
    6.0,
    7.0,
    8.0,
    9.0,
    10.0
  ],
  "per_pressure": {
    "0.1": {
      "completed": 16,
      "converged": 16,
      "failed": 0
    },
    "0.5": {
      "completed": 16,
      "converged": 11,
      "failed": 5
    },
    "1": {
      "completed": 16,
      "converged": 10,
      "failed": 6
    },
    "2": {
      "completed": 16,
      "converged": 8,
      "failed": 8
    },
    "3": {
      "completed": 16,
      "converged": 7,
      "failed": 9
    },
    "4": {
      "completed": 16,
      "converged": 7,
      "failed": 9
    },
    "5": {
      "completed": 15,
      "converged": 7,
      "failed": 8
    },
    "6": {
      "completed": 15,
      "converged": 7,
      "failed": 8
    },
    "7": {
      "completed": 15,
      "converged": 7,
      "failed": 8
    },
    "8": {
      "completed": 15,
      "converged": 7,
      "failed": 8
    },
    "9": {
      "completed": 15,
      "converged": 7,
      "failed": 8
    },
    "10": {
      "completed": 15,
      "converged": 7,
      "failed": 8
    }
  },
  "current_mof": "qmof-9e2ce18",
  "current_pressure": 4.0,
  "mof_set_info": {
    "shard_file": "/workspace/shards/Xe_rear/shard_Xe_4.txt",
    "shard_index": "4",
    "n_mofs": 208
  }
}