{
  "adsorbate": "CO2",
  "server": "0e3a6834f90c",
  "last_update": "2026-04-22T13:30:16.668147+00:00",
  "start_time": "2026-04-22T11:44:56.236846+00:00",
  "total_mofs": 637,
  "pressures": [
    0.1,
    0.5,
    1.0,
    2.0,
    3.0,
    4.0,
    5.0,
    6.0,
    7.0,
    8.0,
    9.0,
    10.0
  ],
  "per_pressure": {
    "0.1": {
      "completed": 464,
      "converged": 396,
      "failed": 68
    },
    "0.5": {
      "completed": 464,
      "converged": 353,
      "failed": 111
    },
    "1": {
      "completed": 464,
      "converged": 338,
      "failed": 126
    },
    "2": {
      "completed": 464,
      "converged": 326,
      "failed": 138
    },
    "3": {
      "completed": 464,
      "converged": 317,
      "failed": 147
    },
    "4": {
      "completed": 464,
      "converged": 317,
      "failed": 147
    },
    "5": {
      "completed": 464,
      "converged": 318,
      "failed": 146
    },
    "6": {
      "completed": 464,
      "converged": 316,
      "failed": 148
    },
    "7": {
      "completed": 464,
      "converged": 312,
      "failed": 152
    },
    "8": {
      "completed": 464,
      "converged": 316,
      "failed": 148
    },
    "9": {
      "completed": 464,
      "converged": 314,
      "failed": 150
    },
    "10": {
      "completed": 464,
      "converged": 317,
      "failed": 147
    }
  },
  "current_mof": "qmof-c19b211",
  "current_pressure": 0.1,
  "mof_set_info": {
    "shard_file": "/workspace/shards/CO2/shard_CO2_0.txt",
    "shard_index": "0",
    "n_mofs": 637
  }
}