{
  "adsorbate": "CO2",
  "server": "0e3a6834f90c",
  "last_update": "2026-04-23T02:00:36.871137+00:00",
  "start_time": "2026-04-22T11:44:56.263886+00:00",
  "total_mofs": 637,
  "pressures": [
    0.1,
    0.5,
    1.0,
    2.0,
    3.0,
    4.0,
    5.0,
    6.0,
    7.0,
    8.0,
    9.0,
    10.0
  ],
  "per_pressure": {
    "0.1": {
      "completed": 635,
      "converged": 534,
      "failed": 101
    },
    "0.5": {
      "completed": 635,
      "converged": 496,
      "failed": 139
    },
    "1": {
      "completed": 635,
      "converged": 499,
      "failed": 136
    },
    "2": {
      "completed": 635,
      "converged": 476,
      "failed": 159
    },
    "3": {
      "completed": 635,
      "converged": 472,
      "failed": 163
    },
    "4": {
      "completed": 635,
      "converged": 470,
      "failed": 165
    },
    "5": {
      "completed": 635,
      "converged": 468,
      "failed": 167
    },
    "6": {
      "completed": 635,
      "converged": 463,
      "failed": 172
    },
    "7": {
      "completed": 635,
      "converged": 465,
      "failed": 170
    },
    "8": {
      "completed": 635,
      "converged": 463,
      "failed": 172
    },
    "9": {
      "completed": 634,
      "converged": 462,
      "failed": 172
    },
    "10": {
      "completed": 634,
      "converged": 460,
      "failed": 174
    }
  },
  "current_mof": "qmof-f7afbf6",
  "current_pressure": 8.0,
  "mof_set_info": {
    "shard_file": "/workspace/shards/CO2/shard_CO2_1.txt",
    "shard_index": "1",
    "n_mofs": 637
  }
}