{
  "adsorbate": "CO2",
  "server": "0e3a6834f90c",
  "last_update": "2026-04-21T16:30:33.116985+00:00",
  "start_time": "2026-04-21T12:17:47.678026+00:00",
  "total_mofs": 637,
  "pressures": [
    0.1,
    0.5,
    1.0,
    2.0,
    3.0,
    4.0,
    5.0,
    6.0,
    7.0,
    8.0,
    9.0,
    10.0
  ],
  "per_pressure": {
    "0.1": {
      "completed": 74,
      "converged": 63,
      "failed": 11
    },
    "0.5": {
      "completed": 74,
      "converged": 51,
      "failed": 23
    },
    "1": {
      "completed": 73,
      "converged": 49,
      "failed": 24
    },
    "2": {
      "completed": 73,
      "converged": 43,
      "failed": 30
    },
    "3": {
      "completed": 73,
      "converged": 43,
      "failed": 30
    },
    "4": {
      "completed": 73,
      "converged": 42,
      "failed": 31
    },
    "5": {
      "completed": 73,
      "converged": 41,
      "failed": 32
    },
    "6": {
      "completed": 73,
      "converged": 41,
      "failed": 32
    },
    "7": {
      "completed": 73,
      "converged": 38,
      "failed": 35
    },
    "8": {
      "completed": 73,
      "converged": 42,
      "failed": 31
    },
    "9": {
      "completed": 73,
      "converged": 40,
      "failed": 33
    },
    "10": {
      "completed": 73,
      "converged": 41,
      "failed": 32
    }
  },
  "current_mof": "qmof-ad90d19",
  "current_pressure": 0.5,
  "mof_set_info": {
    "shard_file": "/workspace/shards/CO2/shard_CO2_0.txt",
    "shard_index": "0",
    "n_mofs": 637
  }
}