{
  "adsorbate": "C2H6",
  "server": "113ac159923b",
  "last_update": "2026-04-22T12:58:26.272936+00:00",
  "start_time": "2026-04-22T11:52:40.497704+00:00",
  "total_mofs": 465,
  "pressures": [
    0.1,
    0.5,
    1.0,
    2.0,
    3.0,
    4.0,
    5.0,
    6.0,
    7.0,
    8.0,
    9.0,
    10.0
  ],
  "per_pressure": {
    "0.1": {
      "completed": 282,
      "converged": 265,
      "failed": 17
    },
    "0.5": {
      "completed": 282,
      "converged": 251,
      "failed": 31
    },
    "1": {
      "completed": 282,
      "converged": 243,
      "failed": 39
    },
    "2": {
      "completed": 281,
      "converged": 225,
      "failed": 56
    },
    "3": {
      "completed": 281,
      "converged": 212,
      "failed": 69
    },
    "4": {
      "completed": 281,
      "converged": 206,
      "failed": 75
    },
    "5": {
      "completed": 281,
      "converged": 203,
      "failed": 78
    },
    "6": {
      "completed": 281,
      "converged": 200,
      "failed": 81
    },
    "7": {
      "completed": 281,
      "converged": 198,
      "failed": 83
    },
    "8": {
      "completed": 281,
      "converged": 195,
      "failed": 86
    },
    "9": {
      "completed": 281,
      "converged": 192,
      "failed": 89
    },
    "10": {
      "completed": 281,
      "converged": 188,
      "failed": 93
    }
  },
  "current_mof": "qmof-b46941a",
  "current_pressure": 1.0,
  "mof_set_info": {
    "shard_file": "/workspace/shards/C2H6/shard_C2H6_5.txt",
    "shard_index": "5",
    "n_mofs": 465
  }
}