{
  "adsorbate": "C2H6",
  "server": "113ac159923b",
  "last_update": "2026-04-21T21:30:16.179985+00:00",
  "start_time": "2026-04-21T12:16:16.334243+00:00",
  "total_mofs": 465,
  "pressures": [
    0.1,
    0.5,
    1.0,
    2.0,
    3.0,
    4.0,
    5.0,
    6.0,
    7.0,
    8.0,
    9.0,
    10.0
  ],
  "per_pressure": {
    "0.1": {
      "completed": 67,
      "converged": 67,
      "failed": 0
    },
    "0.5": {
      "completed": 67,
      "converged": 54,
      "failed": 13
    },
    "1": {
      "completed": 67,
      "converged": 49,
      "failed": 18
    },
    "2": {
      "completed": 67,
      "converged": 46,
      "failed": 21
    },
    "3": {
      "completed": 67,
      "converged": 43,
      "failed": 24
    },
    "4": {
      "completed": 67,
      "converged": 38,
      "failed": 29
    },
    "5": {
      "completed": 66,
      "converged": 37,
      "failed": 29
    },
    "6": {
      "completed": 66,
      "converged": 37,
      "failed": 29
    },
    "7": {
      "completed": 66,
      "converged": 34,
      "failed": 32
    },
    "8": {
      "completed": 66,
      "converged": 37,
      "failed": 29
    },
    "9": {
      "completed": 66,
      "converged": 33,
      "failed": 33
    },
    "10": {
      "completed": 66,
      "converged": 32,
      "failed": 34
    }
  },
  "current_mof": "qmof-28498f0",
  "current_pressure": 4.0,
  "mof_set_info": {
    "shard_file": "/workspace/shards/C2H6/shard_C2H6_1.txt",
    "shard_index": "1",
    "n_mofs": 465
  }
}