{
  "adsorbate": "Xe",
  "server": "xe-server",
  "last_update": "2026-04-21T17:59:47.380507+00:00",
  "start_time": "2026-04-21T12:10:45.186030+00:00",
  "total_mofs": 311,
  "pressures": [
    0.1,
    0.5,
    1.0,
    2.0,
    3.0,
    4.0,
    5.0,
    6.0,
    7.0,
    8.0,
    9.0,
    10.0
  ],
  "per_pressure": {
    "0.1": {
      "completed": 36,
      "converged": 36,
      "failed": 0
    },
    "0.5": {
      "completed": 36,
      "converged": 31,
      "failed": 5
    },
    "1": {
      "completed": 36,
      "converged": 25,
      "failed": 11
    },
    "2": {
      "completed": 36,
      "converged": 20,
      "failed": 16
    },
    "3": {
      "completed": 36,
      "converged": 17,
      "failed": 19
    },
    "4": {
      "completed": 36,
      "converged": 16,
      "failed": 20
    },
    "5": {
      "completed": 36,
      "converged": 16,
      "failed": 20
    },
    "6": {
      "completed": 36,
      "converged": 16,
      "failed": 20
    },
    "7": {
      "completed": 36,
      "converged": 15,
      "failed": 21
    },
    "8": {
      "completed": 36,
      "converged": 14,
      "failed": 22
    },
    "9": {
      "completed": 35,
      "converged": 14,
      "failed": 21
    },
    "10": {
      "completed": 35,
      "converged": 12,
      "failed": 23
    }
  },
  "current_mof": "qmof-08cbfe6",
  "current_pressure": 8.0,
  "mof_set_info": {
    "shard_file": "/workspace/shards/Xe/shard_Xe_0.txt",
    "shard_index": "0",
    "n_mofs": 311
  }
}