{
  "adsorbate": "Xe",
  "server": "xe-server",
  "last_update": "2026-04-21T00:59:20.030981+00:00",
  "start_time": "2026-04-20T09:41:21.929260+00:00",
  "total_mofs": 518,
  "pressures": [
    0.1,
    0.5,
    1.0,
    2.0,
    3.0,
    4.0,
    5.0,
    6.0,
    7.0,
    8.0,
    9.0,
    10.0
  ],
  "per_pressure": {
    "0.1": {
      "completed": 59,
      "converged": 55,
      "failed": 4
    },
    "0.5": {
      "completed": 59,
      "converged": 53,
      "failed": 6
    },
    "1": {
      "completed": 59,
      "converged": 49,
      "failed": 10
    },
    "2": {
      "completed": 59,
      "converged": 43,
      "failed": 16
    },
    "3": {
      "completed": 59,
      "converged": 42,
      "failed": 17
    },
    "4": {
      "completed": 58,
      "converged": 37,
      "failed": 21
    },
    "5": {
      "completed": 58,
      "converged": 36,
      "failed": 22
    },
    "6": {
      "completed": 58,
      "converged": 35,
      "failed": 23
    },
    "7": {
      "completed": 58,
      "converged": 35,
      "failed": 23
    },
    "8": {
      "completed": 58,
      "converged": 33,
      "failed": 25
    },
    "9": {
      "completed": 58,
      "converged": 34,
      "failed": 24
    },
    "10": {
      "completed": 58,
      "converged": 33,
      "failed": 25
    }
  },
  "current_mof": "qmof-8442243",
  "current_pressure": 3.0,
  "mof_set_info": {
    "shard_file": "/workspace/shards/Xe/shard_Xe_4.txt",
    "shard_index": "4",
    "n_mofs": 518
  }
}