{
  "adsorbate": "CO2",
  "server": "fe1e32d71454",
  "last_update": "2026-04-20T14:00:03.675101+00:00",
  "start_time": "2026-04-20T08:46:41.219457+00:00",
  "total_mofs": 637,
  "pressures": [
    0.1,
    0.5,
    1.0,
    2.0,
    3.0,
    4.0,
    5.0,
    6.0,
    7.0,
    8.0,
    9.0,
    10.0
  ],
  "per_pressure": {
    "0.1": {
      "completed": 183,
      "converged": 29,
      "failed": 154
    },
    "0.5": {
      "completed": 183,
      "converged": 30,
      "failed": 153
    },
    "1": {
      "completed": 183,
      "converged": 30,
      "failed": 153
    },
    "2": {
      "completed": 183,
      "converged": 28,
      "failed": 155
    },
    "3": {
      "completed": 183,
      "converged": 28,
      "failed": 155
    },
    "4": {
      "completed": 183,
      "converged": 28,
      "failed": 155
    },
    "5": {
      "completed": 183,
      "converged": 28,
      "failed": 155
    },
    "6": {
      "completed": 183,
      "converged": 28,
      "failed": 155
    },
    "7": {
      "completed": 183,
      "converged": 28,
      "failed": 155
    },
    "8": {
      "completed": 183,
      "converged": 28,
      "failed": 155
    },
    "9": {
      "completed": 183,
      "converged": 28,
      "failed": 155
    },
    "10": {
      "completed": 183,
      "converged": 28,
      "failed": 155
    }
  },
  "current_mof": "qmof-450de13",
  "current_pressure": 0.1,
  "mof_set_info": {
    "shard_file": "/workspace/shards/CO2/shard_CO2_1.txt",
    "shard_index": "1",
    "n_mofs": 637
  }
}