{
  "adsorbate": "C3H8",
  "server": "c4ed440939ed",
  "last_update": "2026-04-24T03:26:56.425186+00:00",
  "start_time": "2026-04-23T12:39:38.232408+00:00",
  "total_mofs": 337,
  "pressures": [
    0.1,
    0.5,
    1.0,
    2.0,
    3.0,
    4.0,
    5.0,
    6.0,
    7.0,
    8.0,
    9.0,
    10.0
  ],
  "per_pressure": {
    "0.1": {
      "completed": 21,
      "converged": 14,
      "failed": 7
    },
    "0.5": {
      "completed": 20,
      "converged": 12,
      "failed": 8
    },
    "1": {
      "completed": 20,
      "converged": 12,
      "failed": 8
    },
    "2": {
      "completed": 20,
      "converged": 9,
      "failed": 11
    },
    "3": {
      "completed": 20,
      "converged": 11,
      "failed": 9
    },
    "4": {
      "completed": 20,
      "converged": 10,
      "failed": 10
    },
    "5": {
      "completed": 20,
      "converged": 8,
      "failed": 12
    },
    "6": {
      "completed": 20,
      "converged": 8,
      "failed": 12
    },
    "7": {
      "completed": 20,
      "converged": 7,
      "failed": 13
    },
    "8": {
      "completed": 20,
      "converged": 8,
      "failed": 12
    },
    "9": {
      "completed": 20,
      "converged": 8,
      "failed": 12
    },
    "10": {
      "completed": 20,
      "converged": 6,
      "failed": 14
    }
  },
  "current_mof": "qmof-c1f4bcc",
  "current_pressure": 0.1,
  "mof_set_info": {
    "shard_file": "/workspace/shards/C3H8/shard_C3H8_6_retry.txt",
    "shard_index": "6",
    "n_mofs": 337
  }
}