{
  "adsorbate": "C3H8",
  "server": "c4ed440939ed",
  "last_update": "2026-04-24T17:42:32.510552+00:00",
  "start_time": "2026-04-23T12:39:38.236261+00:00",
  "total_mofs": 335,
  "pressures": [
    0.1,
    0.5,
    1.0,
    2.0,
    3.0,
    4.0,
    5.0,
    6.0,
    7.0,
    8.0,
    9.0,
    10.0
  ],
  "per_pressure": {
    "0.1": {
      "completed": 39,
      "converged": 29,
      "failed": 10
    },
    "0.5": {
      "completed": 39,
      "converged": 30,
      "failed": 9
    },
    "1": {
      "completed": 38,
      "converged": 20,
      "failed": 18
    },
    "2": {
      "completed": 38,
      "converged": 18,
      "failed": 20
    },
    "3": {
      "completed": 38,
      "converged": 16,
      "failed": 22
    },
    "4": {
      "completed": 38,
      "converged": 15,
      "failed": 23
    },
    "5": {
      "completed": 38,
      "converged": 15,
      "failed": 23
    },
    "6": {
      "completed": 38,
      "converged": 14,
      "failed": 24
    },
    "7": {
      "completed": 38,
      "converged": 13,
      "failed": 25
    },
    "8": {
      "completed": 38,
      "converged": 14,
      "failed": 24
    },
    "9": {
      "completed": 38,
      "converged": 12,
      "failed": 26
    },
    "10": {
      "completed": 38,
      "converged": 12,
      "failed": 26
    }
  },
  "current_mof": "qmof-a4d3459",
  "current_pressure": 0.5,
  "mof_set_info": {
    "shard_file": "/workspace/shards/C3H8/shard_C3H8_5_retry.txt",
    "shard_index": "5",
    "n_mofs": 335
  }
}