{
  "adsorbate": "C3H8",
  "server": "c4ed440939ed",
  "last_update": "2026-04-23T06:29:21.178458+00:00",
  "start_time": "2026-04-22T04:31:48.903269+00:00",
  "total_mofs": 479,
  "pressures": [
    0.1,
    0.5,
    1.0,
    2.0,
    3.0,
    4.0,
    5.0,
    6.0,
    7.0,
    8.0,
    9.0,
    10.0
  ],
  "per_pressure": {
    "0.1": {
      "completed": 443,
      "converged": 404,
      "failed": 39
    },
    "0.5": {
      "completed": 443,
      "converged": 314,
      "failed": 129
    },
    "1": {
      "completed": 442,
      "converged": 283,
      "failed": 159
    },
    "2": {
      "completed": 442,
      "converged": 241,
      "failed": 201
    },
    "3": {
      "completed": 442,
      "converged": 228,
      "failed": 214
    },
    "4": {
      "completed": 442,
      "converged": 215,
      "failed": 227
    },
    "5": {
      "completed": 442,
      "converged": 201,
      "failed": 241
    },
    "6": {
      "completed": 442,
      "converged": 194,
      "failed": 248
    },
    "7": {
      "completed": 442,
      "converged": 191,
      "failed": 251
    },
    "8": {
      "completed": 442,
      "converged": 184,
      "failed": 258
    },
    "9": {
      "completed": 442,
      "converged": 174,
      "failed": 268
    },
    "10": {
      "completed": 442,
      "converged": 175,
      "failed": 267
    }
  },
  "current_mof": "qmof-5b72dfa",
  "current_pressure": 0.5,
  "mof_set_info": {
    "shard_file": "/workspace/shards/C3H8/shard_C3H8_2.txt",
    "shard_index": "2",
    "n_mofs": 479
  }
}