{
  "adsorbate": "N2",
  "server": "svr2",
  "last_update": "2026-04-20T15:29:58.267946+00:00",
  "start_time": "2026-04-19T16:09:31.299556+00:00",
  "total_mofs": 1527,
  "pressures": [
    0.1,
    0.5,
    1.0,
    2.0,
    3.0,
    4.0,
    5.0,
    6.0,
    7.0,
    8.0,
    9.0,
    10.0
  ],
  "per_pressure": {
    "0.1": {
      "completed": 376,
      "converged": 366,
      "failed": 10
    },
    "0.5": {
      "completed": 376,
      "converged": 360,
      "failed": 16
    },
    "1": {
      "completed": 376,
      "converged": 359,
      "failed": 17
    },
    "2": {
      "completed": 376,
      "converged": 357,
      "failed": 19
    },
    "3": {
      "completed": 376,
      "converged": 357,
      "failed": 19
    },
    "4": {
      "completed": 376,
      "converged": 357,
      "failed": 19
    },
    "5": {
      "completed": 376,
      "converged": 357,
      "failed": 19
    },
    "6": {
      "completed": 376,
      "converged": 357,
      "failed": 19
    },
    "7": {
      "completed": 376,
      "converged": 357,
      "failed": 19
    },
    "8": {
      "completed": 376,
      "converged": 357,
      "failed": 19
    },
    "9": {
      "completed": 375,
      "converged": 356,
      "failed": 19
    },
    "10": {
      "completed": 375,
      "converged": 356,
      "failed": 19
    }
  },
  "current_mof": "qmof-beeedc4",
  "current_pressure": 8.0,
  "mof_set_info": {
    "shard_file": "/home/yoonho/multi_gas_package/shards/N2/shard_N2_2.txt",
    "shard_index": "2",
    "n_mofs": 1527
  }
}