{
  "adsorbate": "N2",
  "server": "svr2",
  "last_update": "2026-04-21T21:59:17.903805+00:00",
  "start_time": "2026-04-19T16:09:31.234823+00:00",
  "total_mofs": 1528,
  "pressures": [
    0.1,
    0.5,
    1.0,
    2.0,
    3.0,
    4.0,
    5.0,
    6.0,
    7.0,
    8.0,
    9.0,
    10.0
  ],
  "per_pressure": {
    "0.1": {
      "completed": 878,
      "converged": 848,
      "failed": 30
    },
    "0.5": {
      "completed": 877,
      "converged": 831,
      "failed": 46
    },
    "1": {
      "completed": 877,
      "converged": 830,
      "failed": 47
    },
    "2": {
      "completed": 877,
      "converged": 829,
      "failed": 48
    },
    "3": {
      "completed": 877,
      "converged": 830,
      "failed": 47
    },
    "4": {
      "completed": 877,
      "converged": 830,
      "failed": 47
    },
    "5": {
      "completed": 877,
      "converged": 831,
      "failed": 46
    },
    "6": {
      "completed": 877,
      "converged": 831,
      "failed": 46
    },
    "7": {
      "completed": 877,
      "converged": 831,
      "failed": 46
    },
    "8": {
      "completed": 877,
      "converged": 830,
      "failed": 47
    },
    "9": {
      "completed": 877,
      "converged": 831,
      "failed": 46
    },
    "10": {
      "completed": 877,
      "converged": 831,
      "failed": 46
    }
  },
  "current_mof": "qmof-2dab706",
  "current_pressure": 0.1,
  "mof_set_info": {
    "shard_file": "/home/yoonho/multi_gas_package/shards/N2/shard_N2_0.txt",
    "shard_index": "0",
    "n_mofs": 1528
  }
}